pandas_paddles/__init__.py
pandas_paddles/axis.py
pandas_paddles/closures.py
pandas_paddles/contexts.py
pandas_paddles/operator_helpers.py
pandas_paddles/paddles.py
pandas_paddles/pipe.py
pandas_paddles/util.py
pandas_paddles-1.5.0.dist-info/LICENSE
pandas_paddles-1.5.0.dist-info/METADATA
pandas_paddles-1.5.0.dist-info/WHEEL
pandas_paddles-1.5.0.dist-info/RECORD
