Metadata-Version: 2.1
Name: pandas-paddles
Version: 1.5.0
Summary: Simple, composable selectors for loc[], iloc[], assign() and others for fluent-API style Pandas code.
Home-page: https://github.com/eikevons/pandas-paddles.git
License: MIT
Author: Eike von Seggern
Author-email: eikevons@mailbox.org
Requires-Python: >=3.7.0,<4.0.0
Classifier: Development Status :: 5 - Production/Stable
Classifier: Environment :: Console
Classifier: Intended Audience :: Science/Research
Classifier: License :: OSI Approved :: MIT License
Classifier: Operating System :: OS Independent
Classifier: Programming Language :: Python :: 3
Classifier: Programming Language :: Python :: 3.7
Classifier: Programming Language :: Python :: 3.8
Classifier: Programming Language :: Python :: 3.9
Classifier: Programming Language :: Python :: 3.10
Classifier: Programming Language :: Python :: 3.11
Classifier: Programming Language :: Python :: 3 :: Only
Classifier: Programming Language :: Python :: 3.12
Classifier: Topic :: Scientific/Engineering
Provides-Extra: rtdbuild
Requires-Dist: pandas (>=1,<3)
Requires-Dist: pydata-sphinx-theme (>=0.8.0,<0.9.0) ; extra == "rtdbuild"
Requires-Dist: sphinx (>=4.4.0,<5.0.0) ; extra == "rtdbuild"
Requires-Dist: typing-extensions (>=4.1.1,<5.0.0) ; python_full_version <= "3.7.0"
Project-URL: Repository, https://github.com/eikevons/pandas-paddles.git
